manim_play_timeline/__init__.py
manim_play_timeline-0.1.1.dist-info/LICENSE.txt
manim_play_timeline-0.1.1.dist-info/METADATA
manim_play_timeline-0.1.1.dist-info/WHEEL
manim_play_timeline-0.1.1.dist-info/entry_points.txt
manim_play_timeline-0.1.1.dist-info/RECORD
