Metadata-Version: 2.1
Name: manim-play-timeline
Version: 0.1.1
Summary: A manim plugin providing the function play_timeline to play sequences of independent animations in parallel
Home-page: https://github.com/abul4fia/manim-play-timeline
License: MIT
Author: Abul4fia
Author-email: abul4fia@gmail.com
Requires-Python: >=3.8,<3.12
Classifier: Development Status :: 4 - Beta
Classifier: License :: OSI Approved :: MIT License
Classifier: Natural Language :: English
Classifier: Programming Language :: Python :: 3
Classifier: Programming Language :: Python :: 3.8
Classifier: Programming Language :: Python :: 3.9
Classifier: Programming Language :: Python :: 3.10
Classifier: Programming Language :: Python :: 3.11
Classifier: Programming Language :: Python :: 3.10
Classifier: Programming Language :: Python :: 3.11
Classifier: Programming Language :: Python :: 3.8
Classifier: Programming Language :: Python :: 3.9
Classifier: Topic :: Multimedia :: Graphics
Classifier: Topic :: Multimedia :: Video
Classifier: Topic :: Scientific/Engineering
Requires-Dist: manim (>=0.17)
Project-URL: Repository, https://github.com/abul4fia/manim-play-timeline
